Workbook

Sheet Listas
A2: Albertina Tumba | B2: Proposta enviada | D2: A
A3: Amélia Cassinda | B3: Proposta em negociação | D3: B
A4: David Guedes | B4: Proposta aprovada | D4: C
A5: Elizabete Miguel | B5: Perdida
A6: Luísa Baltazar | B6: Produção / Entrega
A7: Marta de Oliveira
A8: Regina Pompilho

Sheet Capa
A1: GPA ANGOLA CRM COMERCIAL COMPLETO
A5: Pipeline, KPIs, dashboard, instruções de registo e análise comercial automática
A8: 1. PIPELINE Registo integral das propostas, responsáveis, datas, probabilidade, prioridade e valor ponderado. | E8: 2. KPI COMERCIAL Taxas de conversão, ticket médio, negócios aprovados, contactos da semana e ranking por comercial.
A14: 3. DASHBOARD Gráficos automáticos, leitura executiva e indicadores de controlo. | E14: 4. INSTRUÇÕES CRM Normas de preenchimento, cadência de follow-up e responsabilidades comerciais.
A21: Fonte base: relatório consolidado de clientes de 01 a 30 de Junho de 2026. O ficheiro inclui fórmulas automáticas, validações de dados e gráficos prontos para gestão comercial.

Sheet Instruções_CRM
B1: INSTRUÇÕES DE REGISTO NO CRM
B4: 1. Objectivo | C4: Registar todas as oportunidades comerciais com rigor, permitindo controlo do pipeline, previsibilidade de fecho e responsabilização individual.
B5: 2. Quando registar | C5: Toda a proposta deve ser lançada no próprio dia do envio ao cliente. Cada novo contacto, negociação, alteração de probabilidade ou aprovação deve actualizar imediatamente a linha correspondente.
B6: 3. Campos obrigatórios | C6: Data de envio, cliente, serviço, estado da proposta, valor, probabilidade, gestor comercial, próxima acção, próximo contacto e observações objectivas.
B7: 4. Regras de probabilidade | C7: 40% = proposta enviada sem validação; 50% = proposta acompanhada; 60% = cliente em análise activa; 75% = negociação final; 100% = aprovado / adjudicado.
B8: 5. Regra de follow-up | C8: Nenhuma proposta pode ficar apenas com a nota 'aguardamos feedback'. Deve sempre existir próxima acção concreta e data específica de contacto.
B9: 6. Classe do cliente | C9: Classe A = conta estratégica / grande volume; Classe B = cliente recorrente; Classe C = cliente ocasional ou pequeno ticket.
B10: 7. Prioridade | C10: Alta = negócios ≥ 50.000.000 Kz ou probabilidade ≥ 75%; Média = negócios ≥ 5.000.000 Kz ou probabilidade ≥ 50%; Normal = restantes casos.
B11: 8. Estado CRM | C11: Aberto = proposta enviada ou em negociação; Fechado ganho = aprovado / produção; Fechado perdido = perdida.
B12: 9. Responsabilidade do comercial | C12: Cada gestor responde pela actualização semanal da sua carteira, qualidade da informação, precisão da probabilidade e fecho dos dossiers sob sua gestão.
B13: 10. Observação de controlo | C13: O relatório de origem apresenta divergência entre o número de pedidos declarado (31) e o total de linhas individuais detectadas (33). O CRM regista as 33 linhas visíveis para garantir rastreabilidade.

Sheet Pipeline
A1: ID | B1: Data envio | C1: Cliente | D1: Serviço | E1: Estado proposta | F1: Valor proposta | G1: Valor aprovado | H1: Valor perdido | I1: Probabilidade | J1: Gestor comercial | K1: Próxima acção | L1: Próximo contacto | M1: Observações | N1: Dias em aberto | O1: Valor ponderado | P1: Classe cliente | Q1: Prioridade | R1: Estado CRM
A2: 1 | B2: 46204 | C2: COSCAL LIMITADA | D2: Brindes e Materiais de Merchandising | E2: Proposta aprovada | F2: 2755950 | G2: 2755950 | H2: 0 | I2: 1 | J2: Luísa Baltazar | K2: Manter o cliente por perto para obter mais trabalhos | L2: 46240 | M2: Material produzido e entregue com feedback positivo | N2: =IF(B2="","",TODAY()-B2) -> 35 | O2: =F2*I2 -> 2755950 | P2: C | Q2: =IF(OR(F2>=50000000,I2>=0.75),"Alta",IF(OR(F2>=5000000,I2>=0.5),"Média","Normal")) -> Alta | R2: =IF(E2="Proposta aprovada","Fechado ganho",IF(E2="Perdida","Fechado perdido","Aberto")) -> Fechado ganho
A3: 2 | B3: 46213 | C3: COSCAL LIMITADA | D3: Impressão de Flyers | E3: Proposta aprovada | F3: 313500 | G3: 313500 | H3: 0 | I3: 1 | J3: Luísa Baltazar | K3: Manter o cliente por perto para obter mais trabalhos | L3: 46240 | M3: Material produzido e entregue com feedback positivo | N3: =IF(B3="","",TODAY()-B3) -> 26 | O3: =F3*I3 -> 313500 | P3: C | Q3: =IF(OR(F3>=50000000,I3>=0.75),"Alta",IF(OR(F3>=5000000,I3>=0.5),"Média","Normal")) -> Alta | R3: =IF(E3="Proposta aprovada","Fechado ganho",IF(E3="Perdida","Fechado perdido","Aberto")) -> Fechado ganho
A4: 3 | B4: 46211 | C4: ALIANÇA SEGUROS | D4: Impressão de Flyers | E4: Perdida | F4: 3328800 | G4: 0 | H4: 3328800 | I4: 0 | J4: Luísa Baltazar | K4: Focar em outros processos | L4: 46240 | M4: O cliente não especificou o motivo da rejeição | N4: =IF(B4="","",TODAY()-B4) -> 28 | O4: =F4*IB+O4 -> 0 | P4: B | Q4: =IF(OR(F4>=50000000,I4>=0.75),"Alta",IF(OR(F4>=5000000,I4>=0.5),"Média","Normal")) -> Normal | R4: =IF(E4="Proposta aprovada","Fechado ganho",IF(E4="Perdida","Fechado perdido","Aberto")) -> Fechado perdido
A5: 4 | B5: 46204 | C5: FINSTAR | D5: T-Shirts para Lojistas | E5: Proposta aprovada | F5: 21161250 | G5: 21161250 | H5: 0 | I5: 1 | J5: Luísa Baltazar | K5: Pressionar a informação relativamente aos tamanhos para dar início a produção | L5: 46240 | M5: O cliente já partilhou as artes, mas ainda temos em falta os tamanhos | N5: =IF(B5="","",TODAY()-B5) -> 35 | O5: =F5*I5 -> 21161250 | P5: A | Q5: =IF(OR(F5>=50000000,I5>=0.75),"Alta",IF(OR(F5>=5000000,I5>=0.5),"Média","Normal")) -> Alta | R5: =IF(E5="Proposta aprovada","Fechado ganho",IF(E5="Perdida","Fechado perdido","Aberto")) -> Fechado ganho
A6: 5 | B6: 46218 | C6: FINSTAR | D6: T-Shirts para Lojistas (2ª Fase) | E6: Proposta em negociação | F6: 21161250 | G6: 0 | H6: 0 | I6: 0.6 | J6: Luísa Baltazar | K6: Pressionar o envio da PO | L6: 46240 | M6: A PO está em processamento | N6: =IF(B6="","",TODAY()-B6) -> 21 | O6: =F6*I6 -> 12696750 | P6: A | Q6: =IF(OR(F6>=50000000,I6>=0.75),"Alta",IF(OR(F6>=5000000,I6>=0.5),"Média","Normal")) -> Média | R6: =IF(E6="Proposta aprovada","Fechado ganho",IF(E6="Perdida","Fechado perdido","Aberto")) -> Aberto
A7: 6 | B7: 46218 | C7: FINSTAR | D7: Sacos TNT | E7: Proposta aprovada | F7: 1687200 | G7: 1687200 | H7: 0 | I7: 1 | J7: Luísa Baltazar | K7: Manter o contacto com o cliente para obter novas aprovações | L7: 46240 | M7: Material produzido e entregue | N7: =IF(B7="","",TODAY()-B7) -> 21 | O7: =F7*I7 -> 1687200 | P7: A | Q7: =IF(OR(F7>=50000000,I7>=0.75),"Alta",IF(OR(F7>=5000000,I7>=0.5),"Média","Normal")) -> Alta | R7: =IF(E7="Proposta aprovada","Fechado ganho",IF(E7="Perdida","Fechado perdido","Aberto")) -> Fechado ganho
A8: 7 | B8: 46223 | C8: FINSTAR | D8: Materiais Diversos | E8: Perdida | F8: 1508220 | G8: 0 | H8: 1508220 | I8: 0 | J8: Luísa Baltazar | K8: Focar em outros processos | L8: 46240 | M8: O cliente optou por avançar com o fornecedor onde tinham saldo pendente | N8: =IF(B8="","",TODAY()-B8) -> 16 | O8: =F8*I8 -> 0 | P8: A | Q8: =IF(OR(F8>=50000000,I8>=0.75),"Alta",IF(OR(F8>=5000000,I8>=0.5),"Média","Normal")) -> Normal | R8: =IF(E8="Proposta aprovada","Fechado ganho",IF(E8="Perdida","Fechado perdido","Aberto")) -> Fechado perdido
A9: 8 | B9: 46231 | C9: FINSTAR | D9: Fitas Porta Passe Sem Personalização | E9: Proposta aprovada | F9: 79800 | G9: 79800 | H9: 0 | I9: 1 | J9: Luísa Baltazar | K9: Negocias as restantes propostas em aberto | L9: 46240 | M9: O material já foi entregue | N9: =IF(B9="","",TODAY()-B9) -> 8 | O9: =F9*I9 -> 79800 | P9: A | Q9: =IF(OR(F9>=50000000,I9>=0.75),"Alta",IF(OR(F9>=5000000,I9>=0.5),"Média","Normal")) -> Alta | R9: =IF(E9="Proposta aprovada","Fechado ganho",IF(E9="Perdida","Fechado perdido","Aberto")) -> Fechado ganho
A10: 9 | B10: 46212 | C10: IMOCASAIS | D10: Fornecimento de Blocos de nota, canetas Flyers | E10: Perdida | F10: 1385100 | H10: 1385100 | I10: 0 | J10: Luísa Baltazar | K10: Focar em outros processos | L10: 46240 | M10: Devido ao preço, o cliente optou por avançar com outro fornecedor | N10: =IF(B10="","",TODAY()-B10) -> 27 | O10: =F10*I10 -> 0 | P10: C | Q10: =IF(OR(F10>=50000000,I10>=0.75),"Alta",IF(OR(F10>=5000000,I10>=0.5),"Média","Normal")) -> Normal | R10: =IF(E10="Proposta aprovada","Fechado ganho",IF(E10="Perdida","Fechado perdido","Aberto")) -> Fechado perdido
A11: 10 | B11: 46210 | C11: SUEZ | D11: Fornecimento de Flyrs monofolha e tripticos | E11: Proposta em negociação | F11: 6260880 | H11: 0 | I11: 0.5 | J11: Luísa Baltazar | K11: Negociar a modadlidade de pagamento | L11: 46240 | M11: Aguardamos o envio da PO | N11: =IF(B11="","",TODAY()-B11) -> 29 | O11: =F11*I11 -> 3130440 | P11: B | Q11: =IF(OR(F11>=50000000,I11>=0.75),"Alta",IF(OR(F11>=5000000,I11>=0.5),"Média","Normal")) -> Média | R11: =IF(E11="Proposta aprovada","Fechado ganho",IF(E11="Perdida","Fechado perdido","Aberto")) -> Aberto
A12: 11 | B12: 46209 | C12: TEIXERA DUARTE | D12: Fornecimento de Diversos | E12: Proposta aprovada | F12: 758100 | G12: 758100 | H12: 0 | I12: 1 | J12: Luísa Baltazar | K12: Aumentar o fluxo de trabalhos com este cliente | L12: 46240 | M12: Material produzido e entregue | N12: =IF(B12="","",TODAY()-B12) -> 30 | O12: =F12*I12 -> 758100 | P12: B | Q12: =IF(OR(F12>=50000000,I12>=0.75),"Alta",IF(OR(F12>=5000000,I12>=0.5),"Média","Normal")) -> Alta | R12: =IF(E12="Proposta aprovada","Fechado ganho",IF(E12="Perdida","Fechado perdido","Aberto")) -> Fechado ganho
A13: 12 | B13: 46210 | C13: SIAC | D13: Fornecimento de brindes e merchandising | E13: Proposta enviada | F13: 19418760 | G13: 0 | H13: 0 | I13: 0.4 | J13: Luísa Baltazar | K13: Agendar uma reunião com o cliente | L13: 46240 | M13: A nossa proposta está em análise | N13: =IF(B13="","",TODAY()-B13) -> 29 | O13: =F13*I13 -> 7767504 | P13: C | Q13: =IF(OR(F13>=50000000,I13>=0.75),"Alta",IF(OR(F13>=5000000,I13>=0.5),"Média","Normal")) -> Média | R13: =IF(E13="Proposta aprovada","Fechado ganho",IF(E13="Perdida","Fechado perdido","Aberto")) -> Aberto
A14: 13 | B14: 46189 | C14: ENDIAMA | D14: Fornecimento de materiais para outubro rosa | E14: Proposta em negociação | F14: 6958560 | H14: 0 | I14: 0.6 | J14: Luísa Baltazar | K14: Negociar a modadlidade de pagamento | L14: 46240 | M14: Falta o envio da PO, para credibilizar a adjudicação do processo | N14: =IF(B14="","",TODAY()-B14) -> 50 | O14: =F14*I14 -> 4175136 | P14: B | Q14: =IF(OR(F14>=50000000,I14>=0.75),"Alta",IF(OR(F14>=5000000,I14>=0.5),"Média","Normal")) -> Média | R14: =IF(E14="Proposta aprovada","Fechado ganho",IF(E14="Perdida","Fechado perdido","Aberto")) -> Aberto
A15: 14 | B15: 46216 | C15: UNITEL | D15: Canecas de Porcelana e Garrafas Térmica | E15: Proposta enviada | F15: 96124800 | G15: 0 | H15: 0 | I15: 0.4 | J15: Luísa Baltazar | K15: Incentivar o cliente para o envio da contraproposta. | L15: 46240 | M15: O processo de análise das propostas está em curso | N15: =IF(B15="","",MAX(0,TODAY()-B15)) -> 23 | O15: =IF(OR(F15="",I15=""),"",F15*I15) -> 38449920 | P15: A | Q15: Alta | R15: Aberto
A16: 15 | B16: 46218 | C16: CARPINANGOLA/CASAIS | D16: Bloco de Notas e Canetas | E16: Proposta aprovada | F16: 2017800 | G16: 2017800 | H16: 0 | I16: 1 | J16: Luísa Baltazar | K16: Alinhamento com a cliente para obter mais trabalhos | L16: 46240 | M16: O processo de produção está em curso, faremos a entrega no dia 20 de Julho | N16: =IF(B16="","",MAX(0,TODAY()-B16)) -> 21 | O16: =IF(OR(F16="",I16=""),"",F16*I16) -> 2017800 | P16: B | Q16: Alta | R16: Fechado ganho
A17: 16 | B17: 46220 | C17: CEGID/PRIMAVERA | D17: Impressão de Flyers | E17: Proposta aprovada | F17: 445700 | G17: 445700 | H17: 0 | I17: 1 | J17: Luísa Baltazar | K17: Cumprimento do prazo de entrega | L17: 46240 | M17: O processo de produção está em curso, faremos a entrega no dia 20 de Julho | N17: =IF(B17="","",MAX(0,TODAY()-B17)) -> 19 | O17: =IF(OR(F17="",I17=""),"",F17*I17) -> 445700 | P17: B | Q17: Alta | R17: Fechado ganho
A18: 17 | B18: 46220 | C18: FINSTAR/ZAP | D18: T-Shirts para Filda | E18: Proposta enviada | F18: 1966500 | G18: 0 | H18: 0 | I18: 0.5 | J18: Luísa Baltazar | K18: Persuadir a aprovação usando o prazo de entrega do estratégia | L18: 46240 | M18: As propostas ainda estão a ser analisadas | N18: =IF(B18="","",MAX(0,TODAY()-B18)) -> 19 | O18: =IF(OR(F18="",I18=""),"",F18*I18) -> 983250 | P18: A | Q18: Normal | R18: Aberto
A19: 18 | B19: 46219 | C19: SIAC | D19: Totens em Betão | E19: Proposta enviada | F19: 29641900 | G19: 0 | H19: 0 | I19: 0.4 | J19: Luísa Baltazar | K19: Solicitar uma reunião com este cliente | L19: 46240 | M19: A nossa proposta foi submetida para avaliação | N19: =IF(B19="","",MAX(0,TODAY()-B19)) -> 20 | O19: =IF(OR(F19="",I19=""),"",F19*I19) -> 11856760 | P19: C | Q19: Normal | R19: Aberto
A20: 19 | B20: 46234 | C20: ENDIAMA | D20: Tapete para Sala de Espera | E20: Proposta enviada | F20: 21906076 | G20: 0 | H20: 0 | I20: 0.4 | J20: Luísa Baltazar | K20: Apresentar uma proposta com maaterial mais econ | L20: 46240 | M20: O processo de análise das propostas está em curso | N20: =IF(B20="","",MAX(0,TODAY()-B20)) -> 5 | O20: =IF(OR(F20="",I20=""),"",F20*I20) -> 8762430.3 | P20: A | Q20: Alta | R20: Aberto
A21: 20 | B21: 46230 | C21: UNITEL | D21: Fitas Porta Passe | E21: Proposta enviada | F21: 21366450 | G21: 0 | H21: 0 | I21: 0.2 | J21: Luísa Baltazar | K21: Focar em outros processos | L21: 46240 | M21: A contraproposta apresentada pelo cliente está muito abaixo do nosso orçamento e não compensa avançar | N21: =IF(B21="","",MAX(0,TODAY()-B21)) -> 9 | O21: =IF(OR(F21="",I21=""),"",F21*I21) -> 4273290 | P21: A | Q21: Média | R21: Aberto
A22: 21 | B22: 46230 | C22: UNITEL | D22: Capas de Importação | E22: Proposta enviada | F22: 1303020 | G22: 0 | H22: 0 | I22: 0.2 | J22: Luísa Baltazar | K22: Focar em outros processos | L22: 46240 | M22: A contraproposta apresentada pelo cliente está muito abaixo do nosso orçamento e não compensa avançar | N22: =IF(B22="","",MAX(0,TODAY()-B22)) -> 9 | O22: =IF(OR(F22="",I22=""),"",F22*I22) -> 260604 | P22: A | Q22: Alta | R22: Aberto
A23: 22 | B23: 46233 | C23: FINSTAR/ZAP | D23: Letras Recortadas em PVC com Vinil | E23: Proposta enviada | F23: 628995 | G23: 0 | H23: 0 | I23: 0.5 | J23: Luísa Baltazar | K23: Contactar o cliente para pressionar a aprovação | L23: 46240 | M23: A nossa proposta está a ser analisada pelo cliente | N23: =IF(B23="","",MAX(0,TODAY()-B23)) -> 6 | O23: =IF(OR(F23="",I23=""),"",F23*I23) -> 314497.5 | P23: A | Q23: Alta | R23: Fechado ganho
A24: 23 | B24: 46234 | C24: CEGID | D24: Brindes e Materiais de Merchandising | E24: Proposta enviada | F24: 25891680 | G24: 0 | H24: 0 | I24: 0.2 | J24: Luísa Baltazar | K24: Focar em outros processos | L24: 46240 | M24: O nosso concorrente é internacional e a nossa proposta está o dobro do valor | N24: =IF(B24="","",MAX(0,TODAY()-B24)) -> 5 | O24: =IF(OR(F24="",I24=""),"",F24*I24) -> 5178336 | P24: B | Q24: Normal | R24: Aberto
A25: 24 | B25: 46223 | C25: SBM OFFSHORE | D25: Posters em Papel Satim | E25: Proposta aprovada | F25: 940500 | G25: 940500 | H25: 0 | I25: 1 | J25: Luísa Baltazar | K25: Produzir e entregar uma nova amostra ao cliente | L25: 46240 | M25: A amostra anteriormente produzida foi reprovada pelo cliente devido a qualidade de impressão | N25: =IF(B25="","",MAX(0,TODAY()-B25)) -> 16 | O25: =IF(OR(F25="",I25=""),"",F25*I25) -> 940500 | P25: A | Q25: Alta | R25: Aberto
A26: 25 | B26: 46226 | C26: ENDIAMA | D26: Criação e Impressão de Revistas | E26: Proposta enviada | F26: 6433020 | G26: 0 | H26: 0 | I26: 0.4 | J26: Luísa Baltazar | K26: Considerar a possibilidade de apresentar um desconto | L26: 46240 | M26: A nossa proposta está acima do orçamento apresentado pelo cliente | N26: =IF(B26="","",MAX(0,TODAY()-B26)) -> 13 | O26: =IF(OR(F26="",I26=""),"",F26*I26) -> 2573208 | P26: B | Q26: Alta | R26: Aberto
A27: 26 | B27: 46198 | C27: PAY4ALL | D27: Fornecimento de Brindes para a filda | E27: Proposta aprovada | F27: 2106150 | G27: 2106150 | H27: 0 | I27: 1 | J27: Amélia Cassinda | K27: Manter o contacto com o cliente para obter novas aprovações | L27: 46240 | M27: Material produzido e entregue | N27: =IF(B27="","",TODAY()-B27) -> 41 | O27: =F27*I27 -> 2106150 | P27: C | Q27: =IF(OR(F27>=50000000,I27>=0.75),"Alta",IF(OR(F27>=5000000,I27>=0.5),"Média","Normal")) -> Alta | R27: =IF(E27="Proposta aprovada","Fechado ganho",IF(E27="Perdida","Fechado perdido","Aberto")) -> Fechado ganho
A28: 27 | B28: 46209 | C28: XPRINT | D28: Fornecimento de Brindes e Têxtil | E28: Proposta enviada | F28: 2350680 | G28: 0 | H28: 0 | I28: 0.4 | J28: Amélia Cassinda | K28: Considerar a possibilidade de apresentar um desconto | L28: 46240 | M28: Proposta remetida para avaliação | N28: =IF(B28="","",TODAY()-B28) -> 30 | O28: =F28*I28 -> 940272 | P28: B | Q28: =IF(OR(F28>=50000000,I28>=0.75),"Alta",IF(OR(F28>=5000000,I28>=0.5),"Média","Normal")) -> Normal | R28: =IF(E28="Proposta aprovada","Fechado ganho",IF(E28="Perdida","Fechado perdido","Aberto")) -> Aberto
A29: 28 | B29: 46213 | C29: DUBAI INVESTIMETS | D29: Forneciemnto de Brindes | E29: Proposta enviada | F29: 6156000 | G29: 0 | H29: 0 | I29: 0.5 | J29: Amélia Cassinda | K29: Apresentar amostras Físicas e acompanhar o processo | L29: 46240 | M29: Proposta remetida para avaliação | N29: =IF(B29="","",TODAY()-B29) -> 26 | O29: =F29*I29 -> 3078000 | P29: C | Q29: =IF(OR(F29>=50000000,I29>=0.75),"Alta",IF(OR(F29>=5000000,I29>=0.5),"Média","Normal")) -> Média | R29: =IF(E29="Proposta aprovada","Fechado ganho",IF(E29="Perdida","Fechado perdido","Aberto")) -> Aberto
A30: 29 | B30: 46211 | C30: DUBAI INVESTIMETS | D30: Fornecimento de Flyrs | E30: Proposta enviada | F30: 3249000 | H30: 0 | I30: 0.4 | J30: Amélia Cassinda | K30: Apresentar amostras Físicas e acompanhar o processo | L30: 46240 | M30: Proposta remetida para avaliação | N30: =IF(B30="","",TODAY()-B30) -> 28 | O30: =F30*I30 -> 1299600 | P30: C | Q30: =IF(OR(F30>=50000000,I30>=0.75),"Alta",IF(OR(F30>=5000000,I30>=0.5),"Média","Normal")) -> Normal | R30: =IF(E30="Proposta aprovada","Fechado ganho",IF(E30="Perdida","Fechado perdido","Aberto")) -> Aberto
A31: 31 | B31: 46209 | C31: BCGA | D31: Fornecimento de Lenços e gravatas | E31: Perdida | F31: 9095000 | H31: 9095000 | I31: 0 | J31: Amélia Cassinda | K31: Apresentação de disponibilidade para futurod projectos | L31: 46240 | M31: Proposta rejeitada, por causa do tempo de produção e pelo fornecedor não ter o mesmo tecido | N31: =IF(B31="","",TODAY()-B31) -> 30 | O31: =F31*I31 -> 0 | P31: C | Q31: =IF(OR(F31>=50000000,I31>=0.75),"Alta",IF(OR(F31>=5000000,I31>=0.5),"Média","Normal")) -> Média | R31: =IF(E31="Proposta aprovada","Fechado ganho",IF(E31="Perdida","Fechado perdido","Aberto")) -> Fechado perdido
A32: 32 | B32: 46206 | C32: BCGA | D32: Fornecimento de Fita Tulyy | E32: Perdida | F32: 2684700 | H32: 2684700 | I32: 0 | J32: Amélia Cassinda | K32: Apresentação de disponibilidade para futurod projectos | L32: 46240 | M32: Proposta reajustada por falta de amostras físicas | N32: =IF(B32="","",TODAY()-B32) -> 33 | O32: =F32*I32 -> 0 | P32: A | Q32: =IF(OR(F32>=50000000,I32>=0.75),"Alta",IF(OR(F32>=5000000,I32>=0.5),"Média","Normal")) -> Normal | R32: =IF(E32="Proposta aprovada","Fechado ganho",IF(E32="Perdida","Fechado perdido","Aberto")) -> Fechado perdido
A33: 33 | B33: 46182 | C33: SBM OFFSHORE | D33: Impressão de Autocolante | E33: Proposta aprovada | F33: 339150 | G33: 339150 | H33: 0 | I33: 1 | J33: Amélia Cassinda | K33: Entrega do material ao cliente | L33: 46240 | M33: O material está pronto para ser entregue | N33: =IF(B33="","",MAX(0,TODAY()-B33)) -> 57 | O33: =IF(OR(F33="",I33=""),"",F33*I33) -> 339150 | P33: A | Q33: Normal | R33: Fechado ganho
A34: 34 | B34: 46216 | C34: BCGA | D34: Fornecimento de Sacolas | E34: Proposta aprovada | F34: 3135000 | G34: 3135000 | H34: 0 | I34: 1 | J34: Amélia Cassinda | K34: Resolver os impasses dentro do processo | L34: 46240 | M34: Tivemos alguns constrangimentos durante o processo, mas já estão a ser resolvidos | N34: =IF(B34="","",MAX(0,TODAY()-B34)) -> 23 | O34: =IF(OR(F34="",I34=""),"",F34*I34) -> 3135000 | P34: A | Q34: Alta | R34: Fechado ganho
A35: 35 | B35: 46216 | C35: TREVOTECH | D35: Fornecimento de Polos | E35: Perdida | F35: 889200 | G35: 0 | H35: 889200 | I35: 0 | J35: Amélia Cassinda | K35: Desculpar-se com o cliente pelo constrangimento causado no processo | L35: 46240 | M35: Material produzido e entregue | N35: =IF(B35="","",MAX(0,TODAY()-B35)) -> 23 | O35: =IF(OR(F35="",I35=""),"",F35*I35) -> 0 | P35: C | Q35: Normal | R35: Fechado perdido
A36: 36 | B36: 46220 | C36: ANGOLACA | D36: Fornecimento de Materiais Diversos | E36: Proposta enviada | F36: 14248432 | G36: 0 | H36: 0 | I36: 0.5 | J36: Amélia Cassinda | K36: Contactar a cliente para agendar uma reunião | L36: 46240 | M36: Proposta remetida para avaliação | N36: =IF(B36="","",MAX(0,TODAY()-B36)) -> 19 | O36: =IF(OR(F36="",I36=""),"",F36*I36) -> 7124216.2 | P36: C | Q36: Média | R36: Aberto
A37: 37 | B37: 46217 | C37: DUBAI INVESTIMETS | D37: Fornecimento de Garrafas Térmicas | E37: Proposta enviada | F37: 29724360 | G37: 0 | H37: 0 | I37: 0.4 | J37: Amélia Cassinda | K37: Avaliar a possibilidade de dar um desconto | L37: 46240 | M37: Proposta remetida para avaliação | N37: =IF(B37="","",MAX(0,TODAY()-B37)) -> 22 | O37: =IF(OR(F37="",I37=""),"",F37*I37) -> 11889744 | P37: C | Q37: Média | R37: Aberto
A38: 38 | B38: 46220 | C38: FADA | D38: Fornecimento de Brindes | E38: Proposta enviada | F38: 3583000 | G38: 0 | H38: 0 | I38: 0.4 | J38: Amélia Cassinda | K38: Solicitar o ponto de situação da proposta | L38: 46240 | M38: Proposta remetida para avaliação | N38: =IF(B38="","",MAX(0,TODAY()-B38)) -> 19 | O38: =IF(OR(F38="",I38=""),"",F38*I38) -> 1433200 | P38: B | Q38: Média | R38: Aberto
A39: 39 | B39: 46227 | C39: SANLAMALLIAZ | D39: Fornecimento de letras em 3D | E39: Proposta enviada | F39: 4008312 | G39: 0 | H39: 0 | I39: 0.5 | J39: Amélia Cassinda | K39: Solicitar um feedback do orçamento | L39: 46240 | M39: As propostas ainda estão a ser analisadas | N39: =IF(B39="","",MAX(0,TODAY()-B39)) -> 12 | O39: =IF(OR(F39="",I39=""),"",F39*I39) -> 2004156 | P39: A | Q39: Normal | R39: Aberto
A40: 40 | B40: 46225 | C40: CLINICA SAGRADA ESPERANÇA | D40: Fornecimento e aplicação de vinil fosco | E40: Proposta aprovada | F40: 3975230 | G40: 3975230 | H40: 0 | I40: 1 | J40: Amélia Cassinda | K40: Manter o contacto com o cliente para gerar novos negócios | L40: 46240 | M40: O processo de montagem foi concluído | N40: =IF(B40="","",MAX(0,TODAY()-B40)) -> 14 | O40: =IF(OR(F40="",I40=""),"",F40*I40) -> 3975230 | P40: C | Q40: Normal | R40: Aberto
A41: 41 | B41: 46223 | C41: SONILS | D41: Fornecimento de caixa luminoso e placa acrilica | E41: Proposta enviada | F41: 8390400 | G41: 0 | H41: 0 | I41: 0.4 | J41: Amélia Cassinda | K41: Entrar em contacto com o cliente e persuadir o fecho | L41: 46240 | M41: A nossa proposta foi submetida para avaliação | N41: =IF(B41="","",MAX(0,TODAY()-B41)) -> 16 | O41: =IF(OR(F41="",I41=""),"",F41*I41) -> 3356160 | P41: A | Q41: Normal | R41: Fechado ganho
A42: 42 | B42: 46227 | C42: TRANSFUEL | D42: Fornecimento de uniformes | E42: Proposta enviada | F42: 3344864.9 | G42: 0 | H42: 0 | I42: 0.5 | J42: Amélia Cassinda | K42: Entrar em contacto com o cliente e persuadir o fecho | L42: 46240 | M42: A nossa proposta foi submetida para avaliação | N42: =IF(B42="","",MAX(0,TODAY()-B42)) -> 12 | O42: =IF(OR(F42="",I42=""),"",F42*I42) -> 1672432.4 | P42: A | Q42: Alta | R42: Fechado ganho
A43: 43 | B43: 46225 | C43: SBM OFFSHORE | D43: Fornecimento de vinil | E43: Proposta em negociação | F43: 6561940.4 | G43: 0 | H43: 0 | I43: 0.7 | J43: Amélia Cassinda | K43: Entrar em contacto com o cliente e persuadir o fecho | L43: 46240 | M43: Material produzido e entregue | N43: =IF(B43="","",MAX(0,TODAY()-B43)) -> 14 | O43: =IF(OR(F43="",I43=""),"",F43*I43) -> 4593358.3 | P43: C | Q43: Normal | R43: Fechado ganho
A44: 44 | B44: 46233 | C44: SAIPEM | D44: Fornecimento de Brindes | E44: Proposta enviada | F44: 10411050 | G44: 0 | H44: 0 | I44: 0.4 | J44: Amélia Cassinda | K44: Considerar a possibilidade de apresentar um desconto | L44: 46240 | M44: A nossa proposta foi submetida para avaliação | N44: =IF(B44="","",MAX(0,TODAY()-B44)) -> 6 | O44: =IF(OR(F44="",I44=""),"",F44*I44) -> 4164420 | P44: C | Q44: Normal | R44: Aberto
... A50: 50 | B50: 46212 | C50: AFRICANA | D50: Fornecimento de letras em monobloco | E50: Perdida | F50: 12398175 | G50: 0 | H50: 12398175 | I50: 0 | J50: Marta de Oliveira | K50: Focar em outros processos | L50: 46240 | M50: O cliente optou por não avançar com o processo | N50: =IF(B50="","",MAX(0,TODAY()-B50)) -> 27 | O50: =IF(OR(F50="",I50=""),"",F50*I50) -> 0 | P50: A | Q50: Média | R50: Fechado ganho
A51: 51 | B51: 46206 | C51: TRIBUNAL DE CONTAS | D51: Roll Ups | E51: Proposta aprovada | F51: 171000 | G51: 171000 | H51: 0 | I51: 1 | J51: Marta de Oliveira | K51: Dar seguimento a outras negociações | L51: 46240 | M51: Material produzido e entregue | N51: =IF(B51="","",TODAY()-B51) -> 33 | O51: =F51*I51 -> 171000 | P51: C | Q51: =IF(OR(F51>=50000000,I51>=0.75),"Alta",IF(OR(F51>=5000000,I51>=0.5),"Média","Normal")) -> Alta | R51: =IF(E51="Proposta aprovada","Fechado ganho",IF(E51="Perdida","Fechado perdido","Aberto")) -> Fechado ganho
A52: 52 | B52: 46210 | C52: NOSSA SEGUROS | D52: Fornecimento de Material para filda | E52: Proposta aprovada | F52: 2809820 | G52: 2809820 | H52: 0 | I52: 1 | J52: Marta de Oliveira | K52: Manter o contacto com o cliente para obter novas aprovações | L52: 46240 | M52: Material produzido e entregue | N52: =IF(B52="","",TODAY()-B52) -> 29 | O52: =F52*I52 -> 2809820 | P52: A | Q52: =IF(OR(F52>=50000000,I52>=0.75),"Alta",IF(OR(F52>=5000000,I52>=0.5),"Média","Normal")) -> Alta | R52: =IF(E52="Proposta aprovada","Fechado ganho",IF(E52="Perdida","Fechado perdido","Aberto")) -> Fechado ganho
A53: 53 | B53: 46209 | C53: ATO | D53: Fornecimento de brindes para Filda | E53: Proposta aprovada | F53: 7695000 | G53: 7695000 | H53: 0 | I53: 1 | J53: Marta de Oliveira | K53: Dar seguimento a outras negociações | L53: 46240 | M53: Material produzido e entregue | N53: =IF(B53="","",TODAY()-B53) -> 30 | O53: =F53*I53 -> 7695000 | P53: C | Q53: =IF(OR(F53>=50000000,I53>=0.75),"Alta",IF(OR(F53>=5000000,I53>=0.5),"Média","Normal")) -> Alta | R53: =IF(E53="Proposta aprovada","Fechado ganho",IF(E53="Perdida","Fechado perdido","Aberto")) -> Fechado ganho
A54: 54 | B54: 46210 | C54: DISBRA | D54: Fornecimento de sacolas e folhetos | E54: Proposta aprovada | F54: 222300 | G54: 222300 | H54: 0 | I54: 1 | J54: Marta de Oliveira | K54: Apresentar outras soluções ao cliente | L54: 46240 | M54: Material produzido e entregue | N54: =IF(B54="","",TODAY()-B54) -> 29 | O54: =F54*I54 -> 222300 | P54: B | Q54: =IF(OR(F54>=50000000,I54>=0.75),"Alta",IF(OR(F54>=5000000,I54>=0.5),"Média","Normal")) -> Alta | R54: =IF(E54="Proposta aprovada","Fechado ganho",IF(E54="Perdida","Fechado perdido","Aberto")) -> Fechado ganho
A55: 55 | B55: 46219 | C55: NOSSA SEGUROS | D55: Impressão de Flyers | E55: Proposta aprovada | F55: 2530550 | G55: 2530550 | H55: 0 | I55: 1 | J55: Marta de Oliveira | K55: Manter o contacto com o cliente para obter novas aprovações | L55: 46240 | M55: Material produzido e entregue | N55: =IF(B55="","",MAX(0,TODAY()-B55)) -> 20 | O55: =IF(OR(F55="",I55=""),"",F55*I55) -> 2530550 | P55: B | Q55: Alta | R55: Fechado ganho
A56: 56 | B56: 46220 | C56: PROGRAMA ALIMENTAR | D56: Fornecimento de Materiais Diversos | E56: Proposta enviada | F56: 7060875 | G56: 0 | H56: 0 | I56: 0.4 | J56: Marta de Oliveira | K56: Solicitar o feedback deste processo | L56: 46240 | M56: A nossa proposta foi remetida para análise | N56: =IF(B56="","",MAX(0,TODAY()-B56)) -> 19 | O56: =IF(OR(F56="",I56=""),"",F56*I56) -> 2824350 | P56: B | Q56: Normal | R56: Aberto
A57: 57 | B57: 46217 | C57: DIVERSIFICA MAIS | D57: Fornecimento de Passes PVC e Fitas | E57: Proposta enviada | F57: 422712 | G57: 0 | H57: 0 | I57: 0.4 | J57: Marta de Oliveira | K57: Solicitar um feedback do orçamento | L57: 46240 | M57: Apresentamos a proposta e aguardamos feedback do cliente | N57: =IF(B57="","",MAX(0,TODAY()-B57)) -> 22 | O57: =IF(OR(F57="",I57=""),"",F57*I57) -> 169084.8 | P57: B | Q57: Normal | R57: Aberto
A58: 58 | B58: 46219 | C58: ATO | D58: Fornecimento e Montagem de Sinaléticas | E58: Proposta enviada | F58: 1983600 | G58: 0 | H58: 0 | I58: 0.4 | J58: Marta de Oliveira | K58: Contactar o cliente para impulsionar a adjudicação | L58: 46240 | M58: A nossa proposta está em análise | N58: =IF(B58="","",MAX(0,TODAY()-B58)) -> 20 | O58: =IF(OR(F58="",I58=""),"",F58*I58) -> 793440 | P58: B | Q58: Normal | R58: Aberto
A59: 59 | B59: 46220 | C59: VIAÇÃO E TRÂNSITO | D59: Flyers e Roll Ups | E59: Proposta aprovada | F59: 7296000 | G59: 7296000 | H59: 0 | I59: 1 | J59: Marta de Oliveira | K59: Solicitar o envio das artes para a produção | L59: 46240 | M59: As artes estão a ser criadas | N59: =IF(B59="","",MAX(0,TODAY()-B59)) -> 19 | O59: =IF(OR(F59="",I59=""),"",F59*I59) -> 7296000 | P59: A | Q59: Alta | R59: Fechado ganho
A60: 60 | B60: 46226 | C60: PROGRAMA ALIMENTAR | D60: Fornecimento de Materiais Diversos | E60: Proposta enviada | F60: 449730 | G60: 0 | H60: 0 | I60: 0.4 | J60: Marta de Oliveira | K60: Entrar em contacto com o cliente e persuadir o fecho | L60: 46240 | M60: Proposta remetida para avaliação | N60: =IF(B60="","",MAX(0,TODAY()-B60)) -> 13 | O60: =IF(OR(F60="",I60=""),"",F60*I60) -> 179892 | P60: C | Q60: Média | R60: Aberto
A61: 61 | B61: 46227 | C61: AFRICANA | D61: Fornecimento de caixa luminoso e placa em pvc | E61: Proposta em negociação | F61: 4090548 | G61: 0 | H61: 0 | I61: 0.4 | J61: Marta de Oliveira | K61: Avaliar a possibilidade de dar um desconto | L61: 46240 | M61: Proposta remetida para avaliação | N61: =IF(B61="","",MAX(0,TODAY()-B61)) -> 12 | O61: =IF(OR(F61="",I61=""),"",F61*I61) -> 1636219.2 | P61: C | Q61: Média | R61: Aberto
A62: 62 | B62: 46230 | C62: NOSSA SEGUROS | D62: Produção de Folhetos | E62: Proposta aprovada | F62: 1326800 | G62: 1326800 | H62: 0 | I62: 1 | J62: Marta de Oliveira | K62: Solicitar o pagamento da Factura em aberto | L62: 46240 | M62: Material produzido e entregue | N62: =IF(B62="","",MAX(0,TODAY()-B62)) -> 9 | O62: =IF(OR(F62="",I62=""),"",F62*I62) -> 1326800 | P62: A | Q62: Média | R62: Fechado ganho
A63: 63 | B63: 46230 | C63: AFRICANA | D63: Fornecimento de Estrutura Metálica | E63: Proposta em negociação | F63: 6462892 | G63: 0 | H63: 0 | I63: 0.4 | J63: Marta de Oliveira | K63: Marcar um levantamento nas instalações do cliente | L63: 46240 | M63: Já apresentamos o orçamento | N63: =IF(B63="","",MAX(0,TODAY()-B63)) -> 9 | O63: =IF(OR(F63="",I63=""),"",F63*I63) -> 2585156.8 | P63: B | Q63: Alta | R63: Aberto
A64: 64 | B64: 46231 | C64: IMBONO | D64: Fornecimento Polos | E64: Proposta em negociação | F64: 15133500 | G64: 0 | H64: 0 | I64: 0.4 | J64: Marta de Oliveira | K64: Solicitar um feedback do orçamento | L64: 46240 | M64: Já apresentamos as amostras de duas marcas | N64: =IF(B64="","",MAX(0,TODAY()-B64)) -> 8 | O64: =IF(OR(F64="",I64=""),"",F64*I64) -> 6053400 | P64: B | Q64: Normal | R64: Aberto
A65: 65 | B65: 46233 | C65: IGREJA DOS ÚLTIMOS TEMPOS | D65: Fornecimento de Materiais Diversos | E65: Proposta enviada | F65: 30523477 | G65: 0 | H65: 0 | I65: 0.4 | J65: Marta de Oliveira | K65: Procurar um contacto para acelerar a comunicação | L65: 46240 | M65: Vamos solicitar o feedback do orçamento | N65: =IF(B65="","",MAX(0,TODAY()-B65)) -> 6 | O65: =IF(OR(F65="",I65=""),"",F65*I65) -> 12209391 | P65: C | Q65: Normal | R65: Aberto
A66: 66 | B66: 46233 | C66: NOSSA SEGUROS | D66: Fornecimento de Sacolas e Folhetos | E66: Proposta enviada | F66: 397290 | G66: 0 | H66: 0 | I66: 0.6 | J66: Marta de Oliveira | K66: Solicitar o feedbcack do orçamento | L66: 46240 | M66: O cliente manifestou o interesse em avançar connosco | N66: =IF(B66="","",MAX(0,TODAY()-B66)) -> 6 | O66: =IF(OR(F66="",I66=""),"",F66*I66) -> 238374 | P66: A | Q66: Normal | R66: Aberto
A67: 67 | B67: 46199 | C67: GEMCORP | D67: Fornecimento de Materias para Filda | E67: Proposta aprovada | F67: 10151700 | G67: 10151700 | H67: 0 | I67: 1 | J67: Marta de Oliveira | K67: Manter o contacto com o cliente para obter novas aprovações | L67: 46240 | M67: Material produzido e entregue | N67: =IF(B67="","",TODAY()-B67) -> 40 | O67: =F67*I67 -> 10151700 | P67: B | Q67: =IF(OR(F67>=50000000,I67>=0.75),"Alta",IF(OR(F67>=5000000,I67>=0.5),"Média","Normal")) -> Alta | R67: =IF(E67="Proposta aprovada","Fechado ganho",IF(E67="Perdida","Fechado perdido","Aberto")) -> Fechado ganho
A68: 68 | B68: 46204 | C68: ANGOLAUTO | D68: Fornecimento de Brindes | E68: Proposta aprovada | F68: 10203000 | G68: 10203000 | H68: 0 | I68: 1 | J68: David Guedes | K68: Manter o contacto com o cliente para obter novas aprovações | L68: 46240 | M68: Material produzido e entregue | N68: =IF(B68="","",TODAY()-B68) -> 35 | O68: =F68*I68 -> 10203000 | P68: C | Q68: =IF(OR(F68>=50000000,I68>=0.75),"Alta",IF(OR(F68>=5000000,I68>=0.5),"Média","Normal")) -> Alta | R68: =IF(E68="Proposta aprovada","Fechado ganho",IF(E68="Perdida","Fechado perdido","Aberto")) -> Fechado ganho
A69: 69 | B69: 46205 | C69: AUTROMATRIZ | D69: Fornecimento de Tapetes | E69: Proposta aprovada | F69: 526338 | G69: 526338 | H69: 0 | I69: 1 | J69: David Guedes | K69: Dar seguimento a outras negociações | L69: 46240 | M69: Aguardamos o pagamento da Factura | N69: =IF(B69="","",TODAY()-B69) -> 34 | O69: =F69*I69 -> 526338 | P69: B | Q69: =IF(OR(F69>=50000000,I69>=0.75),"Alta",IF(OR(F69>=5000000,I69>=0.5),"Média","Normal")) -> Alta | R69: =IF(E69="Proposta aprovada","Fechado ganho",IF(E69="Perdida","Fechado perdido","Aberto")) -> Fechado ganho
A70: 70 | B70: 46205 | C70: SUAVE | D70: Fornecimento de Bonés | E70: Proposta enviada | F70: 3192000 | G70: 0 | H70: 0 | I70: 0.5 | J70: David Guedes | K70: Entrar em contacto com a cliente para negociar a proposta | L70: 46240 | M70: Proposta remetida para avaliação | N70: 14 | O70: 798000 | P70: B | Q70: Alta | R70: Aberto
A71: 71 | B71: 46205 | C71: ALIANÇA SEGUROS | D71: Forneciemnto de Flyres picotados | E71: Proposta enviada | F71: 4206170 | G71: 0 | H71: 4206170 | I71: 0 | J71: David Guedes | K71: Focar em outros processos | L71: 46240 | M71: O cliente optou por avançar com o fornecedor | N71: =IF(B71="","",TODAY()-B71) -> 34 | O71: =F71*I71 -> 0 | P71: B | Q71: =IF(OR(F71>=50000000,I71>=0.75),"Alta",IF(OR(F71>=5000000,I71>=0.5),"Média","Normal")) -> Normal | R71: =IF(E71="Proposta aprovada","Fechado ganho",IF(E71="Perdida","Fechado perdido","Aberto")) -> Aberto
A72: 72 | B72: 46211 | C72: DP-WORLD | D72: Fornecimeto de Brindes | E72: Proposta aprovada | F72: 3024990 | G72: 3024990 | H72: 0 | I72: 1 | J72: David Guedes | K72: Manter o contacto com o cliente para obter novas aprovações | L72: 46240 | M72: Material produzido e entregue | N72: =IF(B72="","",TODAY()-B72) -> 28 | O72: =F72*I72 -> 3024990 | P72: C | Q72: =IF(OR(F72>=50000000,I72>=0.75),"Alta",IF(OR(F72>=5000000,I72>=0.5),"Média","Normal")) -> Alta | R72: =IF(E72="Proposta aprovada","Fechado ganho",IF(E72="Perdida","Fechado perdido","Aberto")) -> Fechado ganho
A73: 73 | B73: 46213 | C73: RHUANITO | D73: Fornecimento de Flyres e têxtil | E73: Proposta enviada | F73: 687420 | I73: 0.4 | J73: David Guedes | K73: Voltar a contactar o cliente para obter o ponto de situação | L73: 46240 | M73: Proposta remetida para avaliação | N73: =IF(B73="","",TODAY()-B73) -> 26 | O73: =F73*I73 -> 274968 | P73: C | Q73: =IF(OR(F73>=50000000,I73>=0.75),"Alta",IF(OR(F73>=5000000,I73>=0.5),"Média","Normal")) -> Normal | R73: =IF(E73="Proposta aprovada","Fechado ganho",IF(E73="Perdida","Fechado perdido","Aberto")) -> Aberto
A74: 74 | B74: 46213 | C74: KERO | D74: Fornecimeto de Brindes | E74: Proposta enviada | F74: 221160 | H74: 0 | I74: 0.4 | J74: David Guedes | K74: Solicitar o ponto de situação da proposta | L74: 46240 | M74: Proposta remetida para avaliação | N74: =IF(B74="","",TODAY()-B74) -> 26 | O74: =F74*I74 -> 88464 | P74: C | Q74: =IF(OR(F74>=50000000,I74>=0.75),"Alta",IF(OR(F74>=5000000,I74>=0.5),"Média","Normal")) -> Normal | R74: =IF(E74="Proposta aprovada","Fechado ganho",IF(E74="Perdida","Fechado perdido","Aberto")) -> Aberto
A75: 75 | B75: 46220 | C75: DP WORLD | D75: Placas em PVC com Vinil | E75: Proposta em negociação | F75: 1962624 | G75: 0 | H75: 0 | I75: 0.5 | J75: David Guedes | K75: Persuadir a aprovação | L75: 46209 | M75: Já oferecemos um desconto na proposta | N75: =IF(B75="","",MAX(0,TODAY()-B75)) -> 19 | O75: =IF(OR(F75="",I75=""),"",F75*I75) -> 981312 | P75: B | Q75: Alta | R75: Aberto
A76: 76 | B76: 46219 | C76: DP WORLD | D76: Quadros em Acrílico para Documentos | E76: Proposta enviada | F76: 1590300 | G76: 0 | H76: 0 | I76: 0.5 | J76: David Guedes | K76: Considerar a possibilidade de apresentar um desconto | L76: 46240 | M76: A nossa proposta está a ser analisada pelo cliente | N76: =IF(B76="","",MAX(0,TODAY()-B76)) -> 20 | O76: =IF(OR(F76="",I76=""),"",F76*I76) -> 795150 | P76: B | Q76: Alta | R76: Aberto
A77: 77 | B77: 46218 | C77: DP WORLD | D77: Fornecimento de Materiais Diversos | E77: Proposta enviada | F77: 1133502 | G77: 0 | H77: 0 | I77: 0.5 | J77: David Guedes | K77: Entrar em contacto com o cliente e persuadir o fecho | L77: 46240 | M77: Enviamos a proposta e aguardamos feedback do cliente | N77: =IF(B77="","",MAX(0,TODAY()-B77)) -> 21 | O77: =IF(OR(F77="",I77=""),"",F77*I77) -> 566751 | P77: B | Q77: Alta | R77: Aberto
A78: 78 | B78: 46217 | C78: AUTOMATRIZ | D78: Fornecimento e Aplicação de Lona | E78: Proposta em negociação | F78: 405840 | G78: 0 | H78: 0 | I78: 0.5 | J78: David Guedes | K78: Voltar a contactar o cliente para obter o ponto de situação | L78: 46240 | M78: A princípio rejeitamos a produção da amostra, mas vamos analisar melhor | N78: =IF(B78="","",MAX(0,TODAY()-B78)) -> 22 | O78: =IF(OR(F78="",I78=""),"",F78*I78) -> 202920 | P78: B | Q78: Normal | R78: Aberto
A79: 79 | B79: 46225 | C79: ACCESS BANK | D79: Fornecimento de brindes | E79: Proposta enviada | F79: 4858000 | G79: 0 | H79: 0 | I79: 0.4 | J79: David Guedes | K79: Solicitar um feedback do orçamento | L79: 46240 | M79: Proposta remetida para avaliação | N79: =IF(B79="","",MAX(0,TODAY()-B79)) -> 14 | O79: =IF(OR(F79="",I79=""),"",F79*I79) -> 1943200 | P79: B | Q79: Média | R79: Aberto
A80: 80 | B80: 46223 | C80: AUTOMATRIZ | D80: Fornecimento de vinil e letreiro luminoso | E80: Proposta enviada | F80: 28706340 | H80: 0 | I80: 0.3 | J80: David Guedes | K80: Solicitar um feedback do orçamento | L80: 46240 | M80: Proposta remetida para avaliação | N80: =IF(B80="","",MAX(0,TODAY()-B80)) -> 16 | O80: =IF(OR(F80="",I80=""),"",F80*I80) -> 8611902 | P80: B | Q80: Alta | R80: Aberto
A81: 81 | B81: 46234 | C81: CENTRO ÓPTICO | D81: Máquinas Calculadoras Personalizadas | E81: Proposta enviada | F81: 1532160 | G81: 0 | H81: 0 | I81: 0.4 | J81: David Guedes | K81: Entrar em contacto com o cliente para uma possível negociação | L81: 46240 | M81: Fazer o acompanhamento do processo | N81: =IF(B81="","",MAX(0,TODAY()-B81)) -> 5 | O81: =IF(OR(F81="",I81=""),"",F81*I81) -> 612864 | P81: C | Q81: Alta | R81: Aberto
A82: 82 | B82: 46206 | C82: PRODEL | D82: Fornecimento de pastas | E82: Proposta enviada | F82: 2567596.1 | G82: 0 | H82: 0 | I82: 0.3 | J82: José Neto | K82: Solicitar PD da proposta | L82: 46240 | M82: Proposta remetida para avaliação | N82: =IF(B82="","",TODAY()-B82) -> 33 | O82: =F82*I82 -> 770278.84 | P82: B | Q82: =IF(OR(F82>=50000000,I82>=0.75),"Alta",IF(OR(F82>=5000000,I82>=0.5),"Média","Normal")) -> Normal | R82: =IF(E82="Proposta aprovada","Fechado ganho",IF(E82="Perdida","Fechado perdido","Aberto")) -> Aberto
A83: 83 | B83: 46199 | C83: NESTLÉ | D83: Fornecimento de sacolas de papel | E83: Proposta aprovada | F83: 855000 | G83: 855000 | H83: 0 | I83: 1 | J83: José Neto | K83: Negociar as restantes propostas em aberto | L83: 46240 | M83: Processo em curso | N83: =IF(B83="","",TODAY()-B83) -> 40 | O83: =F83*I83 -> 855000 | P83: B | Q83: =IF(OR(F83>=50000000,I83>=0.75),"Alta",IF(OR(F83>=5000000,I83>=0.5),"Média","Normal")) -> Alta | R83: =IF(E83="Proposta aprovada","Fechado ganho",IF(E83="Perdida","Fechado perdido","Aberto")) -> Fechado ganho
A84: 84 | B84: 46210 | C84: PRODEL | D84: Fornecimento de Tapetes | E84: Proposta enviada | F84: 28581282 | G84: 0 | H84: 0 | I84: 0.5 | J84: José Neto | K84: Negociar com o cliente, considerar a possibilidade de desconto, marcar uma reunião | L84: 46240 | M84: Proposta remetida para avaliação | N84: =IF(B84="","",TODAY()-B84) -> 29 | O84: =F84*I84 -> 14290641 | P84: B | Q84: =IF(OR(F84>=50000000,I84>=0.75),"Alta",IF(OR(F84>=5000000,I84>=0.5),"Média","Normal")) -> Média | R84: =IF(E84="Proposta aprovada","Fechado ganho",IF(E84="Perdida","Fechado perdido","Aberto")) -> Aberto
A85: 85 | B85: 46211 | C85: JUMUCUZA | D85: Fornecimento de protedores auditivos | E85: Proposta enviada | F85: 953610 | G85: 0 | H85: 0 | I85: 0.4 | J85: José Neto | K85: Solicitar o ponto de situação da proposta | L85: 46240 | M85: Proposta remetida para avaliação, juntos com as ficha técnica | N85: =IF(B85="","",TODAY()-B85) -> 28 | O85: =F85*I85 -> 381444 | P85: C | Q85: =IF(OR(F85>=50000000,I85>=0.75),"Alta",IF(OR(F85>=5000000,I85>=0.5),"Média","Normal")) -> Normal | R85: =IF(E85="Proposta aprovada","Fechado ganho",IF(E85="Perdida","Fechado perdido","Aberto")) -> Aberto
A86: 86 | B86: 46213 | C86: CERTAVE | D86: Fornecimento de sinaletica | E86: Proposta enviada | F86: 1997394 | H86: 0 | I86: 0.4 | J86: José Neto | K86: Monitorizar o proc. De adjudicação e manter disponibilidade para envetuais ajustes | L86: 46240 | M86: Proposta remetida para avaliação, juntos com as ficha técnica | N86: =IF(B86="","",TODAY()-B86) -> 26 | O86: =F86*I86 -> 798957.6 | P86: C | Q86: =IF(OR(F86>=50000000,I86>=0.75),"Alta",IF(OR(F86>=5000000,I86>=0.5),"Média","Normal")) -> Normal | R86: =IF(E86="Proposta aprovada","Fechado ganho",IF(E86="Perdida","Fechado perdido","Aberto")) -> Aberto
A87: 87 | B87: 46216 | C87: BANCO BNI | D87: Impressão de Flyers | E87: Perdida | F87: 881448 | G87: 0 | H87: 881448 | I87: 0 | J87: José Neto | K87: Apresentar outras soluções ao cliente | L87: 46240 | M87: O cliente optou por avançar com outro fornecedor | N87: =IF(B87="","",MAX(0,TODAY()-B87)) -> 23 | O87: =IF(OR(F87="",I87=""),"",F87*I87) -> 0 | P87: C | Q87: Normal | R87: Aberto
A88: 88 | B88: 46217 | C88: PRODEL | D88: Plotagem de Viatura | E88: Proposta enviada | F88: 1539000 | G88: 0 | H88: 0 | I88: 0.4 | J88: José Neto | K88: Considerar a possibilidade de apresentar um desconto | L88: 46240 | M88: A nossa proposta está a ser analisada pelo cliente | N88: =IF(B88="","",MAX(0,TODAY()-B88)) -> 22 | O88: =IF(OR(F88="",I88=""),"",F88*I88) -> 615600 | P88: B | Q88: Média | R88: Aberto
A89: 89 | B89: 46217 | C89: INDÚSTRIAS TOPACK | D89: Coletes Multibolso e Cartões de Visita | E89: Proposta enviada | F89: 2374050 | G89: 0 | H89: 0 | I89: 0.4 | J89: José Neto | K89: Contactar o cliente para negociar a proposta | L89: 46240 | M89: Apresentamos a proposta e aguardamos feedback do cliente | N89: =IF(B89="","",MAX(0,TODAY()-B89)) -> 22 | O89: =IF(OR(F89="",I89=""),"",F89*I89) -> 949620 | P89: C | Q89: Normal | R89: Aberto
A90: 90 | B90: 46206 | C90: ENDIAMA | D90: Fornecimento De Brindes | E90: Proposta aprovada | F90: 2539350 | G90: 2539350 | H90: 0 | I90: 1 | J90: Ilídio Pedro | K90: Manter o contacto com o cliente para obter novas aprovações | L90: 46240 | M90: Material produzido e entregue com feedback positivo | N90: =IF(B90="","",TODAY()-B90) -> 33 | O90: =F90*I90 -> 2539350 | P90: B | Q90: =IF(OR(F90>=50000000,I90>=0.75),"Alta",IF(OR(F90>=5000000,I90>=0.5),"Média","Normal")) -> Alta | R90: =IF(E90="Proposta aprovada","Fechado ganho",IF(E90="Perdida","Fechado perdido","Aberto")) -> Fechado ganho
A91: 91 | B91: 46210 | C91: ACQUA GLOBAL | D91: Fornecimento de Pins | E91: Proposta aprovada | F91: 2109000 | G91: 2109000 | H91: 0 | I91: 1 | J91: Ilídio Pedro | K91: Apresentar outras soluções ao cliente | L91: 46240 | M91: Acompanhar o processo até ao fecho para assegurar a entrega na data prevista | N91: =IF(B91="","",TODAY()-B91) -> 29 | O91: =F91*I91 -> 2109000 | P91: C | Q91: =IF(OR(F91>=50000000,I91>=0.75),"Alta",IF(OR(F91>=5000000,I91>=0.5),"Média","Normal")) -> Alta | R91: =IF(E91="Proposta aprovada","Fechado ganho",IF(E91="Perdida","Fechado perdido","Aberto")) -> Fechado ganho
A92: 92 | B92: 46209 | C92: OMATAPALO | D92: Fornecimento De Placas sinaleticas | E92: Proposta enviada | F92: 21909090 | H92: 0 | I92: 0.2 | J92: Ilídio Pedro | K92: Solicitar o ponto de situação da proposta | L92: 46240 | M92: O cliente não respondeu ao nosso e-mail, mas tem pouca chances de ser aprovada a nossa proposta | N92: =IF(B92="","",TODAY()-B92) -> 30 | O92: =F92*I92 -> 4381818 | P92: C | Q92: =IF(OR(F92>=50000000,I92>=0.75),"Alta",IF(OR(F92>=5000000,I92>=0.5),"Média","Normal")) -> Média | R92: =IF(E92="Proposta aprovada","Fechado ganho",IF(E92="Perdida","Fechado perdido","Aberto")) -> Aberto
A93: 93 | B93: 46220 | C93: POLITEJO | D93: Impressão de Vinil Autocolante | E93: Proposta aprovada | F93: 49590 | G93: 49590 | H93: 0 | I93: 1 | J93: Ilídio Pedro | K93: Manter o contacto com o cliente para gerar novos negócios | L93: 46240 | M93: O material já foi produzido e entregue | N93: =IF(B93="","",MAX(0,TODAY()-B93)) -> 19 | O93: =IF(OR(F93="",I93=""),"",F93*I93) -> 49590 | P93: C | Q93: Média | R93: Fechado ganho
A94: 94 | B94: 46217 | C94: RÁDIO NACIONAL DE ANGOLA | D94: Brindes para Filda | E94: Perdida | F94: 3243300 | G94: 0 | H94: 3243300 | I94: 0 | J94: Ilídio Pedro | K94: Focar em outros processos | L94: 46240 | M94: A parceria proposta pelo cliente era apenas benéfica para eles | N94: =IF(B94="","",MAX(0,TODAY()-B94)) -> 22 | O94: =IF(OR(F94="",I94=""),"",F94*I94) -> 0 | P94: C | Q94: Baixa | R94: Fechado perdido
A95: 95 | B95: 46217 | C95: SONANGOL PESQUISA E PRODUÇÃO | D95: Brindes para Filda | E95: Proposta aprovada | F95: 7927560 | G95: 7927560 | H95: 0 | I95: 1 | J95: Ilídio Pedro | K95: Manter o cliente por perto para obter mais trabalhos | L95: 46240 | M95: Material produzido e entregue com feedback positivo | N95: =IF(B95="","",MAX(0,TODAY()-B95)) -> 22 | O95: =IF(OR(F95="",I95=""),"",F95*I95) -> 7927560 | P95: C | Q95: Alta | R95: Fechado ganho
A96: 96 | B96: 46227 | C96: NOX,LDA | D96: Fornecimento de canetas | E96: Proposta em negociação | F96: 684000 | G96: 0 | H96: 0 | I96: 0.4 | J96: Ilídio Pedro | K96: Voltar a contactar o cliente para obter o ponto de situação | L96: 46240 | M96: A nossa proposta está em análise | N96: =IF(B96="","",MAX(0,TODAY()-B96)) -> 12 | O96: =IF(OR(F96="",I96=""),"",F96*I96) -> 273600 | P96: B | Q96: Normal | R96: Aberto
A97: 97 | B97: 46225 | C97: ENDIAMA, EP | D97: Fornecimento de carimbo seco | E97: Proposta aprovada | F97: 250800 | G97: 250800 | H97: 0 | I97: 1 | J97: Ilídio Pedro | K97: Manter o contacto com o cliente para obter novas aprovações | L97: 46240 | M97: O material já foi produzido e entregue | N97: =IF(B97="","",MAX(0,TODAY()-B97)) -> 14 | O97: =IF(OR(F97="",I97=""),"",F97*I97) -> 250800 | P97: B | Q97: Normal | R97: Fechado ganho
A98: 98 | B98: 46231 | C98: SÁ - MACHADO | D98: Placas Sinaléticas | E98: Proposta enviada | F98: 2516014 | G98: 0 | H98: 0 | I98: 0.4 | J98: Ilídio Pedro | K98: Contactar o cliente por telemóvel para solicitar o feedback da proposta | L98: 46240 | M98: A proposta foi apresentada mas não tivemos feedback do cliente | N98: =IF(B98="","",MAX(0,TODAY()-B98)) -> 8 | O98: =IF(OR(F98="",I98=""),"",F98*I98) -> 1006405.6 | P98: C | Q98: Normal | R98: Aberto
A99: 99 | B99: 46233 | C99: NESTLÉ | D99: Roll Ups e Bancadas | E99: Proposta enviada | F99: 795150 | G99: 0 | H99: 0 | I99: 0.8 | J99: Ilídio Pedro | K99: Pressionar o envio da PO | L99: 46240 | M99: A proposta foi aprovada, aguardando a PO para dar seguimento a produção | N99: =IF(B99="","",MAX(0,TODAY()-B99)) -> 6 | O99: =IF(OR(F99="",I99=""),"",F99*I99) -> 636120 | P99: B | Q99: Normal | R99: Aberto
A100: 100 | B100: 46205 | C100: PUREGLASS | D100: Fornecimento de polos | E100: Proposta aprovada | F100: 489069 | G100: 489069 | H100: 0 | I100: 1 | J100: Fernando Leite | K100: Manter o contacto com o cliente para obter novas aprovações | L100: 46240 | M100: Material produzido e entregue | N100: =IF(B100="","",MAX(0,TODAY()-B100)) -> 34 | O100: =IF(OR(F100="",I100=""),"",F100*I100) -> 489069 | P100: B | Q100: Média | R100: Fechado ganho
A101: 101 | B101: 46205 | C101: BAXTTER | D101: Fornecimento de brindes | E101: Perdida | F101: 1272240 | G101: 0 | H101: 1272240 | I101: 0 | J101: Fernando Leite | K101: Apresentar outras soluções ao cliente | L101: 46240 | M101: O cliente informou que a nossa proposta está muito alta em relação ao Budget deles | N101: =IF(B101="","",MAX(0,TODAY()-B101)) -> 34 | O101: =IF(OR(F101="",I101=""),"",F101*I101) -> 0 | P101: C | Q101: Média | R101: Fechado perdido
A102: 102 | B102: 46208 | C102: GRUPO CAJUEIRO | D102: Fornecimento de cartões de visitas | E102: Proposta aprovada | F102: 193800 | G102: 193800 | H102: 0 | I102: 1 | J102: Fernando Leite | K102: Manter o contacto com o cliente para obter novos trabalhos | L102: 46240 | M102: Material produzido e entregue | N102: =IF(B102="","",MAX(0,TODAY()-B102)) -> 31 | O102: 371945.52 | P102: B | Q102: Alta | R102: Fechado ganho
A103: 103 | B103: 46211 | C103: PUREGLASS | D103: Fornecimento de T-sirts, Autocolantes e Cartões de Visita | E103: Proposta aprovada | F103: 706800 | G103: 706800 | H103: 0 | I103: 1 | J103: Fernando Leite | K103: Manter o contacto com o cliente para obter novos trabalhos | L103: 46240 | M103: Material produzido e entregue | N103: =IF(B103="","",MAX(0,TODAY()-B103)) -> 28 | O103: =F103*I103 -> 706800 | P103: B | Q103: =IF(OR(F103>=50000000,I103>=0.75),"Alta",IF(OR(F103>=5000000,I103>=0.5),"Média","Normal")) -> Alta | R103: =IF(E103="Proposta aprovada","Fechado ganho",IF(E103="Perdida","Fechado perdido","Aberto")) -> Fechado ganho
A104: 104 | B104: 46213 | C104: 5 LINHAS | D104: Fornecimento de diversos | E104: Proposta enviada | F104: 8468775 | H104: 0 | I104: 0.4 | J104: Fernando Leite | K104: Solicitar o ponto de situação da proposta | L104: 46240 | M104: Proposta remetida para avaliação | N104: =IF(B104="","",MAX(0,TODAY()-B104)) -> 26 | O104: =F104*I104 -> 3387510 | P104: B | Q104: =IF(OR(F104>=50000000,I104>=0.75),"Alta",IF(OR(F104>=5000000,I104>=0.5),"Média","Normal")) -> Média | R104: =IF(E104="Proposta aprovada","Fechado ganho",IF(E104="Perdida","Fechado perdido","Aberto")) -> Aberto
A105: 105 | B105: 46213 | C105: SAAS SISTEMAS TECNOLOGIAS | D105: Fornecimento de passes | E105: Proposta aprovada | F105: 29640 | G105: 29640 | H105: 0 | I105: 1 | J105: Fernando Leite | K105: Apresentar outras soluções ao cliente | L105: 46240 | M105: Material produzido e entregue | N105: =IF(B105="","",MAX(0,TODAY()-B105)) -> 26 | O105: =F105*I105 -> 29640 | P105: C | Q105: =IF(OR(F105>=50000000,I105>=0.75),"Alta",IF(OR(F105>=5000000,I105>=0.5),"Média","Normal")) -> Alta | R105: =IF(E105="Proposta aprovada","Fechado ganho",IF(E105="Perdida","Fechado perdido","Aberto")) -> Fechado ganho
...

Sheet KPIs_Comerciais
A1: KPIs AUTOMÁTICOS POR COMERCIAL
A4: Comercial | B4: N.º propostas | C4: Volume proposto | D4: Volume aprovado | E4: Volume perdido | F4: Pipeline ponderado | G4: Ticket médio | H4: Taxa conversão | I4: N.º aprovadas | J4: N.º abertas | K4: Contactos próximos 7 dias | L4: Negócios alta prioridade | M4: Desempenho
A5: Amélia Cassinda | B5: =COUNTIF(Pipeline!$J$2:$J$111,A5) -> 23 | C5: =SUMIF(Pipeline!$J$2:$J$111,A5,Pipeline!$F$2:$F$111) -> 1.9626971e+08 | D5: =SUMIF(Pipeline!$J$2:$J$111,A5,Pipeline!$G$2:$G$111) -> 9641030 | E5: =SUMIF(Pipeline!$J$2:$J$111,A5,Pipeline!$H$2:$H$111) -> 12668900 | F5: =SUMIF(Pipeline!$J$2:$J$111,A5,Pipeline!$O$2:$O$111) -> 82964376 | G5: =IF(B5=0,0,C5/B5) -> 8533465.8 | H5: =IF(C5=0,0,D5/C5) -> 0.049121333 | I5: =COUNTIFS(Pipeline!$J$2:$J$111,A5,Pipeline!$E$2:$E$111,"Proposta aprovada") -> 5 | J5: =COUNTIFS(Pipeline!$J$2:$J$111,A5,Pipeline!$R$2:$R$111,"Aberto") -> 13 | K5: =COUNTIFS(Pipeline!$J$2:$J$111,A5,Pipeline!$L$2:$L$111,">="&TODAY(),Pipeline!$L$2:$L$111,"<="&TODAY()+7) -> 23 | L5: =COUNTIFS(Pipeline!$J$2:$J$111,A5,Pipeline!$Q$2:$Q$111,"Alta") -> 4 | M5: =IF(H5>=0.2,"Excelente",IF(H5>=0.1,"Bom",IF(H5>0,"Baixo","Crítico"))) -> Baixo
A6: David Guedes | B6: =COUNTIF(Pipeline!$J$2:$J$111,A6) -> 14 | C6: =SUMIF(Pipeline!$J$2:$J$111,A6,Pipeline!$F$2:$F$111) -> 62249844 | D6: =SUMIF(Pipeline!$J$2:$J$111,A6,Pipeline!$G$2:$G$111) -> 13754328 | E6: =SUMIF(Pipeline!$J$2:$J$111,A6,Pipeline!$H$2:$H$111) -> 4206170 | F6: =SUMIF(Pipeline!$J$2:$J$111,A6,Pipeline!$O$2:$O$111) -> 28629859 | G6: =IF(B6=0,0,C6/B6) -> 4446417.4 | H6: =IF(C6=0,0,D6/C6) -> 0.22095361 | I6: =COUNTIFS(Pipeline!$J$2:$J$111,A6,Pipeline!$E$2:$E$111,"Proposta aprovada") -> 3 | J6: =COUNTIFS(Pipeline!$J$2:$J$111,A6,Pipeline!$R$2:$R$111,"Aberto") -> 11 | K6: =COUNTIFS(Pipeline!$J$2:$J$111,A6,Pipeline!$L$2:$L$111,">="&TODAY(),Pipeline!$L$2:$L$111,"<="&TODAY()+7) -> 13 | L6: =COUNTIFS(Pipeline!$J$2:$J$111,A6,Pipeline!$Q$2:$Q$111,"Alta") -> 9 | M6: =IF(H6>=0.2,"Excelente",IF(H6>=0.1,"Bom",IF(H6>0,"Baixo","Crítico"))) -> Excelente
A7: Ilídio Pedro | B7: =COUNTIF(Pipeline!$J$2:$J$111,A7) -> 10 | C7: =SUMIF(Pipeline!$J$2:$J$111,A7,Pipeline!$F$2:$F$111) -> 42023854 | D7: =SUMIF(Pipeline!$J$2:$J$111,A7,Pipeline!$G$2:$G$111) -> 12876300 | E7: =SUMIF(Pipeline!$J$2:$J$111,A7,Pipeline!$H$2:$H$111) -> 3243300 | F7: =SUMIF(Pipeline!$J$2:$J$111,A7,Pipeline!$O$2:$O$111) -> 19174244 | G7: =IF(B7=0,0,C7/B7) -> 4202385.4 | H7: =IF(C7=0,0,D7/C7) -> 0.30640455 | I7: =COUNTIFS(Pipeline!$J$2:$J$111,A7,Pipeline!$E$2:$E$111,"Proposta aprovada") -> 5 | J7: =COUNTIFS(Pipeline!$J$2:$J$111,A7,Pipeline!$R$2:$R$111,"Aberto") -> 4 | K7: =COUNTIFS(Pipeline!$J$2:$J$111,A7,Pipeline!$L$2:$L$111,">="&TODAY(),Pipeline!$L$2:$L$111,"<="&TODAY()+7) -> 10 | L7: =COUNTIFS(Pipeline!$J$2:$J$111,A7,Pipeline!$Q$2:$Q$111,"Alta") -> 3 | M7: =IF(H7>=0.2,"Excelente",IF(H7>=0.1,"Bom",IF(H7>0,"Baixo","Crítico"))) -> Excelente
A8: Fernando Leite | B8: =COUNTIF(Pipeline!$J$2:$J$111,A8) -> 12 | C8: =SUMIF(Pipeline!$J$2:$J$111,A8,Pipeline!$F$2:$F$111) -> 26970129 | D8: =SUMIF(Pipeline!$J$2:$J$111,A8,Pipeline!$G$2:$G$111) -> 1863909 | E8: =SUMIF(Pipeline!$J$2:$J$111,A8,Pipeline!$H$2:$H$111) -> 9741015 | F8: =SUMIF(Pipeline!$J$2:$J$111,A8,Pipeline!$O$2:$O$111) -> 8238410.5 | G8: =IF(B8=0,0,C8/B8) -> 2247510.8 | H8: =IF(C8=0,0,D8/C8) -> 0.069110126 | I8: =COUNTIFS(Pipeline!$J$2:$J$111,A8,Pipeline!$E$2:$E$111,"Proposta aprovada") -> 5 | J8: =COUNTIFS(Pipeline!$J$2:$J$111,A8,Pipeline!$R$2:$R$111,"Aberto") -> 5 | K8: =COUNTIFS(Pipeline!$J$2:$J$111,A8,Pipeline!$L$2:$L$111,">="&TODAY(),Pipeline!$L$2:$L$111,"<="&TODAY()+7) -> 12 | L8: =COUNTIFS(Pipeline!$J$2:$J$111,A8,Pipeline!$Q$2:$Q$111,"Alta") -> 4 | M8: =IF(H8>=0.2,"Excelente",IF(H8>=0.1,"Bom",IF(H8>0,"Baixo","Crítico"))) -> Baixo
A9: Luísa Baltazar | B9: =COUNTIF(Pipeline!$J$2:$J$111,A9) -> 25 | C9: =SUMIF(Pipeline!$J$2:$J$111,A9,Pipeline!$F$2:$F$111) -> 2.9544381e+08 | D9: =SUMIF(Pipeline!$J$2:$J$115,A9,Pipeline!$G$2:$G$115) -> 30159800 | E9: =SUMIF(Pipeline!$J$2:$J$111,A9,Pipeline!$H$2:$H$111) -> 6222120 | F9: =SUMIF(Pipeline!$J$2:$J$111,A9,Pipeline!$O$2:$O$111) -> 49126134 | G9: =IF(B9=0,0,C9/B9) -> 11817752 | H9: =IF(C9=0,0,D9/C9) -> 0.10208303 | I9: =COUNTIFS(Pipeline!$J$2:$J$111,A9,Pipeline!$E$2:$E$111,"Proposta aprovada") -> 9 | J9: =COUNTIFS(Pipeline!$J$2:$J$111,A9,Pipeline!$R$2:$R$111,"Aberto") -> 13 | K9: =COUNTIFS(Pipeline!$J$2:$J$111,A9,Pipeline!$L$2:$L$111,">="&TODAY(),Pipeline!$L$2:$L$111,"<="&TODAY()+7) -> 25 | L9: =COUNTIFS(Pipeline!$J$2:$J$111,A9,Pipeline!$Q$2:$Q$111,"Alta") -> 14 | M9: =IF(H9>=0.2,"Excelente",IF(H9>=0.1,"Bom",IF(H9>0,"Baixo","Crítico"))) -> Bom
A10: Marta de Oliveira | B10: =COUNTIF(Pipeline!$J$2:$J$111,A10) -> 18 | C10: =SUMIF(Pipeline!$J$2:$J$111,A10,Pipeline!$F$2:$F$111) -> 1.1112597e+08 | D10: =SUMIF(Pipeline!$J$2:$J$111,A10,Pipeline!$G$2:$G$111) -> 32203170 | E10: =SUMIF(Pipeline!$J$2:$J$111,A10,Pipeline!$H$2:$H$111) -> 12398175 | F10: =SUMIF(Pipeline!$J$2:$J$111,A10,Pipeline!$O$2:$O$111) -> 58892478 | G10: =IF(B10=0,0,C10/B10) -> 6173664.9 | H10: =IF(C10=0,0,D10/C10) -> 0.28978978 | I10: =COUNTIFS(Pipeline!$J$2:$J$111,A10,Pipeline!$E$2:$E$111,"Proposta aprovada") -> 8 | J10: =COUNTIFS(Pipeline!$J$2:$J$111,A10,Pipeline!$R$2:$R$111,"Aberto") -> 9 | K10: =COUNTIFS(Pipeline!$J$2:$J$111,A10,Pipeline!$L$2:$L$111,">="&TODAY(),Pipeline!$L$2:$L$111,"<="&TODAY()+7) -> 18 | L10: =COUNTIFS(Pipeline!$J$2:$J$111,A10,Pipeline!$Q$2:$Q$111,"Alta") -> 8 | M10: =IF(H10>=0.2,"Excelente",IF(H10>=0.1,"Bom",IF(H10>0,"Baixo","Crítico"))) -> Excelente
A11: José Neto | B11: =COUNTIF(Pipeline!$J$2:$J$111,A11) -> 8 | C11: =SUMIF(Pipeline!$J$2:$J$111,A11,Pipeline!$F$2:$F$111) -> 39749380 | D11: =SUMIF(Pipeline!$J$2:$J$111,A11,Pipeline!$G$2:$G$111) -> 855000 | E11: =SUMIF(Pipeline!$J$2:$J$111,A11,Pipeline!$H$2:$H$111) -> 881448 | F11: =SUMIF(Pipeline!$J$2:$J$111,A11,Pipeline!$O$2:$O$111) -> 18661541 | G11: =IF(B11=0,0,C11/B11) -> 4968672.5 | H11: =IF(C11=0,0,D11/C11) -> 0.021509769 | I11: =COUNTIFS(Pipeline!$J$2:$J$111,A11,Pipeline!$E$2:$E$111,"Proposta aprovada") -> 1 | J11: =COUNTIFS(Pipeline!$J$2:$J$111,A11,Pipeline!$R$2:$R$111,"Aberto") -> 7 | K11: =COUNTIFS(Pipeline!$J$2:$J$111,A11,Pipeline!$L$2:$L$111,">="&TODAY(),Pipeline!$L$2:$L$111,"<="&TODAY()+7) -> 8 | L11: =COUNTIFS(Pipeline!$J$2:$J$111,A11,Pipeline!$Q$2:$Q$111,"Alta") -> 1 | M11: =IF(H11>=0.2,"Excelente",IF(H11>=0.1,"Bom",IF(H11>0,"Baixo","Crítico"))) -> Baixo
A12: TOTAL EQUIPA | B12: =SUM(B5:B11) -> 110 | C12: =SUM(C5:C11) -> 7.738327e+08 | D12: =SUM(D5:D11) -> 101353537 | E12: =SUM(E5:E11) -> 49361128 | F12: =SUM(F5:F11) -> 2.1036587e+08 | G12: =IF(B12=0,0,C12/B12) -> 7034842.7 | H12: =IF(C12=0,0,D12/C12) -> 0.13097603 | I12: =SUM(I5:I11) -> 36 | J12: =SUM(J5:J11) -> 62 | K12: =SUM(K5:K11) -> 109 | L12: =SUM(L5:L11) -> 43 | M12: Síntese

Sheet Comparativo_Semanas
A1: COMPARATIVO DAS 2 ÚLTIMAS SEMANAS
A4: Descrição | B4: 01 - 30 Junho 2026 | C4: 01 – 31 Julho 2026 | D4: Variação
A5: N.º de pedidos (declarado) | B5: 113 | C5: 110 | D5: =IF(B5=0,0,C5/B5-1) -> -0.026548673
A6: N.º de linhas no pipeline | B6: 113 | C6: 111 | D6: =IF(B6=0,0,C6/B6-1) -> -0.017699115
A7: Total de propostas | B7: 7.5484513e+08 | C7: 7.738327e+08 | D7: =IF(B7=0,0,C7/B7-1) -> 0.025154264
A8: Total aprovado | B8: 57094130 | C8: 101353537 | D8: =IF(B8=0,0,C8/B8-1) -> 0.77520067
A9: Total perdido | B9: 26060058 | C9: 49361128 | D9: =IF(B9=0,0,C9/B9-1) -> 0.89412962
A10: Taxa de conversão | B10: =B8/B7 -> 0.075636879 | C10: =C8/C7 -> 0.13097603 | D10: =D8/D7 -> 30.817863

Sheet Dashboard
A1: DASHBOARD EXECUTIVO DO CRM
A4: N.º registos | C4: Volume proposto | E4: Volume aprovado | G4: Taxa conversão
A5: =COUNTA(Pipeline!$A$2:$A$102) -> 101 | C5: =SUM(Pipeline!$F$2:$F$111) -> 7.738327e+08 | E5: =SUM(Pipeline!$G$2:$G$111) -> 101353537 | G5: =IF(C5=0,0,E5/C5) -> 0.13097603
A8: Pipeline ponderado | C8: Probabilidade média | E8: Alta prioridade | G8: Contactos próximos 7 dias
A9: =SUM(Pipeline!$O$2:$O$111) -> 3.7065543e+08 | C9: =AVERAGE(Pipeline!$I$2:$I$111) -> 0.57 | E9: =COUNTIF(Pipeline!$Q$2:$Q$111,"Alta") -> 43 | G9: =COUNTIFS(Pipeline!$L$2:$L$111,">="&TODAY(),Pipeline!$L$2:$L$111,"<="&TODAY()+7) -> 109
A12: Leitura automática: o CRM calcula o valor ponderado por oportunidade, classifica a prioridade, controla o follow-up e apresenta o desempenho de cada comercial. Actualize apenas as células de registo e deixe as colunas de fórmula intactas.
J13: Estado | K13: N.º
J14: Proposta enviada | K14: =COUNTIF(Pipeline!$E$2:$E$111,J14) -> 52
J15: Proposta em negociação | K15: =COUNTIF(Pipeline!$E$2:$E$111,J15) -> 11
J16: Proposta aprovada | K16: =COUNTIF(Pipeline!$E$2:$E$111,J16) -> 36
J17: Perdida | K17: =COUNTIF(Pipeline!$E$2:$E$111,J17) -> 11
J20: Comercial | K20: Volume | L20: Aprovado | M20: Ponderado
J21: =KPIs_Comerciais!A5 -> Amélia Cassinda | K21: =KPIs_Comerciais!C5 -> 1.9626971e+08 | L21: =KPIs_Comerciais!D5 -> 9641030 | M21: =KPIs_Comerciais!F5 -> 82964376
J22: =KPIs_Comerciais!A6 -> David Guedes | K22: =KPIs_Comerciais!C6 -> 62249844 | L22: =KPIs_Comerciais!D6 -> 13754328 | M22: =KPIs_Comerciais!F6 -> 28629859
J23: =KPIs_Comerciais!A7 -> Ilídio Pedro | K23: =KPIs_Comerciais!C7 -> 42023854 | L23: =KPIs_Comerciais!D7 -> 12876300 | M23: =KPIs_Comerciais!F7 -> 19174244
J24: =KPIs_Comerciais!A8 -> Fernando Leite | K24: =KPIs_Comerciais!C8 -> 26970129 | L24: =KPIs_Comerciais!D8 -> 1863909 | M24: =KPIs_Comerciais!F8 -> 8238410.5
J25: =KPIs_Comerciais!A9 -> Luísa Baltazar | K25: =KPIs_Comerciais!C9 -> 2.9544381e+08 | L25: =KPIs_Comerciais!D9 -> 30159800 | M25: 49126134
J26: =KPIs_Comerciais!A10 -> Marta de Oliveira | K26: =KPIs_Comerciais!C10 -> 1.1112597e+08 | L26: =KPIs_Comerciais!D10 -> 32203170 | M26: =KPIs_Comerciais!F10 -> 58892478
J27: =KPIs_Comerciais!A11 -> José Neto | K27: =KPIs_Comerciais!C11 -> 39749380 | L27: =KPIs_Comerciais!D11 -> 855000 | M27: =KPIs_Comerciais!F11 -> 18661541
